hmcis_packs/__init__.py
hmcis_packs/Accruals/__init__.py
hmcis_packs/Accruals/accruals_data.py
hmcis_packs/FinanceDB/__init__.py
hmcis_packs/FinanceDB/dataBase.py
hmcis_packs/budget_mapping/__init__.py
hmcis_packs/budget_mapping/mapping.py
hmcis_packs/clean/__init__.py
hmcis_packs/clean/cleaner.py
hmcis_packs/fixed_assets/FA.py
hmcis_packs/fixed_assets/IFRS16.py
hmcis_packs/fixed_assets/__init__.py
hmcis_packs/hml/__init__.py
hmcis_packs/hml/mobility_lab_data.py
hmcis_packs/initials/__init__.py
hmcis_packs/initials/initial_data.py
hmcis_packs/logger/__init__.py
hmcis_packs/logger/logger_config.py
hmcis_packs/masterdata/__init__.py
hmcis_packs/masterdata/acc_osv.py
hmcis_packs/masterdata/acc_tb.py
hmcis_packs/masterdata/customers.py
hmcis_packs/masterdata/master_data.py
hmcis_packs/masterdata/translation.py
hmcis_packs/masterdata/vendors.py
hmcis_packs/ob_adjustments/__init__.py
hmcis_packs/ob_adjustments/ob_adjsts.py
hmcis_packs/parsers/__init__.py
hmcis_packs/parsers/exceldata.py
hmcis_packs/parsers/txtdata.py
hmcis_packs/pivots/__init__.py
hmcis_packs/pivots/make_pivot.py
hmcis_packs/soap_mdx/__init__.py
hmcis_packs/soap_mdx/soap_mdx_client.py
hmcis_packs/utils/__init__.py
hmcis_packs/utils/decorators.py
hmcis_packs/utils/xlsxinfo.py
hmcis_packs-0.1.26.dist-info/METADATA
hmcis_packs-0.1.26.dist-info/WHEEL
hmcis_packs-0.1.26.dist-info/top_level.txt
hmcis_packs-0.1.26.dist-info/RECORD
