Metadata-Version: 2.4
Name: hmcis-packs
Version: 0.1.26
Summary: This project aims to be HMCIS Pack for date muggling
Requires-Python: >=3.13
Requires-Dist: chardet>=5.2.0
Requires-Dist: colorama>=0.4.6
Requires-Dist: dateparser>=1.2.2
Requires-Dist: jinja2>=3.1.6
Requires-Dist: openpyxl>=3.1.5
Requires-Dist: pandas>=2.3.1
Requires-Dist: psycopg2>=2.9.10
Requires-Dist: pywin32>=310; platform_system == "Windows"
Requires-Dist: pyyaml>=6.0.2
Requires-Dist: requests>=2.32.4
Requires-Dist: ruff>=0.12.4
Requires-Dist: setuptools>=80.9.0
Requires-Dist: twine>=6.2.0
Requires-Dist: xlwings>=0.33
